undetected_chromedriver/__init__.py
undetected_chromedriver/cdp.py
undetected_chromedriver/devtool.py
undetected_chromedriver/dprocess.py
undetected_chromedriver/options.py
undetected_chromedriver/patcher.py
undetected_chromedriver/reactor.py
undetected_chromedriver/webelement.py
undetected_chromedriver_arthur-3.4.9.dist-info/LICENSE
undetected_chromedriver_arthur-3.4.9.dist-info/METADATA
undetected_chromedriver_arthur-3.4.9.dist-info/WHEEL
undetected_chromedriver_arthur-3.4.9.dist-info/top_level.txt
undetected_chromedriver_arthur-3.4.9.dist-info/RECORD
