Metadata-Version: 2.1
Name: undetected-chromedriver-arthur
Version: 3.4.9
Summary: ('(just an impatient fix for headless bug as: https://github.com/ultrafunkamsterdam/undetected-chromedriver/issues/1252#issuecomment-1544900464),can remove anytime once the main stream updated',)
Home-page: https://github.com/ppLorins/undetected-chromedriver/tree/fix-headless-version-issue
Author: UltrafunkAmsterdam
Author-email: info@blackhat-security.nl
License: GPL-3.0
Platform: UNKNOWN
Classifier: License :: OSI Approved :: GNU General Public License v3 (GPLv3)
Classifier: Programming Language :: Python :: 3
Classifier: Programming Language :: Python :: 3.7
Classifier: Programming Language :: Python :: 3.8
Classifier: Programming Language :: Python :: 3.9
Classifier: Programming Language :: Python :: 3.10
Classifier: Programming Language :: Python :: 3.11
License-File: LICENSE
Requires-Dist: selenium (>=4.0.0)
Requires-Dist: requests
Requires-Dist: websockets
